gllm_inference.cpython-312-x86_64-linux-gnu.so
gllm_inference.pyi
gllm_inference/__init__.pyi
gllm_inference/constants.pyi
gllm_inference/builder/__init__.pyi
gllm_inference/builder/_build_invoker.pyi
gllm_inference/builder/build_em_invoker.pyi
gllm_inference/builder/build_lm_invoker.pyi
gllm_inference/builder/build_lm_request_processor.pyi
gllm_inference/builder/build_output_parser.pyi
gllm_inference/catalog/__init__.pyi
gllm_inference/catalog/catalog.pyi
gllm_inference/catalog/lm_request_processor_catalog.pyi
gllm_inference/catalog/prompt_builder_catalog.pyi
gllm_inference/em_invoker/__init__.pyi
gllm_inference/em_invoker/azure_openai_em_invoker.pyi
gllm_inference/em_invoker/bedrock_em_invoker.pyi
gllm_inference/em_invoker/cohere_em_invoker.pyi
gllm_inference/em_invoker/em_invoker.pyi
gllm_inference/em_invoker/google_em_invoker.pyi
gllm_inference/em_invoker/jina_em_invoker.pyi
gllm_inference/em_invoker/langchain_em_invoker.pyi
gllm_inference/em_invoker/openai_compatible_em_invoker.pyi
gllm_inference/em_invoker/openai_em_invoker.pyi
gllm_inference/em_invoker/twelevelabs_em_invoker.pyi
gllm_inference/em_invoker/twelvelabs_em_invoker.pyi
gllm_inference/em_invoker/voyage_em_invoker.pyi
gllm_inference/em_invoker/langchain/__init__.pyi
gllm_inference/em_invoker/langchain/em_invoker_embeddings.pyi
gllm_inference/em_invoker/schema/__init__.pyi
gllm_inference/em_invoker/schema/bedrock.pyi
gllm_inference/em_invoker/schema/cohere.pyi
gllm_inference/em_invoker/schema/google.pyi
gllm_inference/em_invoker/schema/jina.pyi
gllm_inference/em_invoker/schema/langchain.pyi
gllm_inference/em_invoker/schema/openai.pyi
gllm_inference/em_invoker/schema/openai_compatible.pyi
gllm_inference/em_invoker/schema/twelvelabs.pyi
gllm_inference/em_invoker/schema/voyage.pyi
gllm_inference/em_invoker/vector_fuser/__init__.pyi
gllm_inference/em_invoker/vector_fuser/build_vector_fuser.pyi
gllm_inference/em_invoker/vector_fuser/sum_vector_fuser.pyi
gllm_inference_binary-0.5.133.dist-info/METADATA
gllm_inference_binary-0.5.133.dist-info/WHEEL
gllm_inference_binary-0.5.133.dist-info/top_level.txt
gllm_inference_binary-0.5.133.dist-info/RECORD
