Metadata-Version: 2.2
Name: gllm-inference-binary
Version: 0.5.133
Summary: A library containing components related to model inferences in Gen AI applications.
Author-email: Henry Wicaksono <henry.wicaksono@gdplabs.id>, "Delfia N. A. Putri" <delfia.n.a.putri@gdplabs.id>
Requires-Python: <3.14,>=3.11
Requires-Dist: gllm-core-binary<0.5.0,>=0.3.0
Requires-Dist: aiohttp<4.0.0,>=3.12.14
Requires-Dist: filetype<2.0.0,>=1.2.0
Requires-Dist: httpx<0.29.0,>=0.28.0
Requires-Dist: jinja2<4.0.0,>=3.1.4
Requires-Dist: jsonref<2.0.0,>=1.1.0
Requires-Dist: jsonschema<5.0.0,>=4.24.0
Requires-Dist: langchain<0.4.0,>=0.3.8
Requires-Dist: numpy<2.0.0,>=1.26; python_version < "3.12"
Requires-Dist: numpy<3.0.0,>=1.26; python_version >= "3.12" and python_version < "3.13"
Requires-Dist: numpy<3.0.0,>=2.2; python_version >= "3.13"
Requires-Dist: pandas<3.0.0,>=2.2.3
Requires-Dist: prompt-toolkit<4.0.0,>=3.0.0
Requires-Dist: protobuf<7.0.0,>=5.29.4
Requires-Dist: python-magic<0.5.0,>=0.4.27; sys_platform != "win32"
Requires-Dist: python-magic-bin<0.5.0,>=0.4.14; sys_platform == "win32"
Requires-Dist: sentencepiece<0.3.0,>=0.2.0
Provides-Extra: dev
Requires-Dist: coverage<8.0.0,>=7.4.4; extra == "dev"
Requires-Dist: mypy<2.0.0,>=1.15.0; extra == "dev"
Requires-Dist: pre-commit<4.0.0,>=3.7.0; extra == "dev"
Requires-Dist: pytest<9.0.0,>=8.1.1; extra == "dev"
Requires-Dist: pytest-asyncio<0.24.0,>=0.23.6; extra == "dev"
Requires-Dist: pytest-cov<6.0.0,>=5.0.0; extra == "dev"
Requires-Dist: ruff<0.7.0,>=0.6.7; extra == "dev"
Provides-Extra: anthropic
Requires-Dist: anthropic<0.61.0,>=0.60.0; extra == "anthropic"
Provides-Extra: bedrock
Requires-Dist: aioboto3<16.0.0,>=15.0.0; extra == "bedrock"
Provides-Extra: cohere
Requires-Dist: cohere<6.0.0,>=5.18.0; extra == "cohere"
Provides-Extra: datasaur
Requires-Dist: openai<3.0.0,>=2.7.0; extra == "datasaur"
Provides-Extra: google
Requires-Dist: google-genai<2.0.0,>=1.52.0; extra == "google"
Provides-Extra: huggingface
Requires-Dist: huggingface-hub<0.31.0,>=0.30.0; extra == "huggingface"
Requires-Dist: transformers<5.0.0,>=4.52.0; extra == "huggingface"
Provides-Extra: litellm
Requires-Dist: litellm<1.80.0,>=1.70.0; extra == "litellm"
Provides-Extra: livekit
Requires-Dist: livekit<2.0.0,>=1.0.23; extra == "livekit"
Requires-Dist: livekit-agents<2.0.0,>=1.3.12; extra == "livekit"
Requires-Dist: soxr<2.0.0,>=1.0.0; extra == "livekit"
Provides-Extra: openai
Requires-Dist: openai<3.0.0,>=2.7.0; extra == "openai"
Provides-Extra: portkey-ai
Requires-Dist: portkey-ai<2.0.0,>=1.14.4; extra == "portkey-ai"
Provides-Extra: twelvelabs
Requires-Dist: twelvelabs<2.0.0,>=1.1.0; extra == "twelvelabs"
Provides-Extra: voyage
Requires-Dist: voyageai<0.4.0,>=0.3.0; python_version < "3.13" and extra == "voyage"
Provides-Extra: xai
Requires-Dist: xai_sdk<2.0.0,>=1.0.0; extra == "xai"
